[
  {
    "ContainingType": "GAM106ASM.Controllers.AuthController",
    "Method": "Login",
    "RelativePath": "api/Auth/login",
    "HttpMethod": "POST",
    "IsController": true,
    "Order": 0,
    "Parameters": [
      {
        "Name": "request",
        "Type": "GAM106ASM.Controllers.LoginRequest",
        "IsRequired": true
      }
    ],
    "ReturnTypes": []
  },
  {
    "ContainingType": "GAM106ASM.Controllers.AuthController",
    "Method": "GetCurrentUser",
    "RelativePath": "api/Auth/me",
    "HttpMethod": "GET",
    "IsController": true,
    "Order": 0,
    "Parameters": [],
    "ReturnTypes": []
  },
  {
    "ContainingType": "GAM106ASM.Controllers.AuthController",
    "Method": "Register",
    "RelativePath": "api/Auth/register",
    "HttpMethod": "POST",
    "IsController": true,
    "Order": 0,
    "Parameters": [
      {
        "Name": "request",
        "Type": "GAM106ASM.Controllers.RegisterRequest",
        "IsRequired": true
      }
    ],
    "ReturnTypes": []
  },
  {
    "ContainingType": "GAM106ASM.Controllers.CharacterController",
    "Method": "UpdateCharacterSkin",
    "RelativePath": "api/Character/{characterId}/skin",
    "HttpMethod": "PUT",
    "IsController": true,
    "Order": 0,
    "Parameters": [
      {
        "Name": "characterId",
        "Type": "System.Int32",
        "IsRequired": true
      },
      {
        "Name": "dto",
        "Type": "GAM106ASM.Controllers.UpdateSkinDto",
        "IsRequired": true
      }
    ],
    "ReturnTypes": []
  },
  {
    "ContainingType": "GAM106ASM.Controllers.CharacterController",
    "Method": "GetCharacterByPlayerId",
    "RelativePath": "api/Character/{playerId}",
    "HttpMethod": "GET",
    "IsController": true,
    "Order": 0,
    "Parameters": [
      {
        "Name": "playerId",
        "Type": "System.Int32",
        "IsRequired": true
      }
    ],
    "ReturnTypes": []
  },
  {
    "ContainingType": "GAM106ASM.Controllers.CharacterController",
    "Method": "CheckCharacterExists",
    "RelativePath": "api/Character/check/{playerId}",
    "HttpMethod": "GET",
    "IsController": true,
    "Order": 0,
    "Parameters": [
      {
        "Name": "playerId",
        "Type": "System.Int32",
        "IsRequired": true
      }
    ],
    "ReturnTypes": []
  },
  {
    "ContainingType": "GAM106ASM.Controllers.CharacterController",
    "Method": "CreateCharacter",
    "RelativePath": "api/Character/create",
    "HttpMethod": "POST",
    "IsController": true,
    "Order": 0,
    "Parameters": [
      {
        "Name": "dto",
        "Type": "GAM106ASM.Controllers.CreateCharacterDto",
        "IsRequired": true
      }
    ],
    "ReturnTypes": []
  },
  {
    "ContainingType": "GAM106ASM.Controllers.GameInfoController",
    "Method": "GetAllGameModes",
    "RelativePath": "api/GameInfo/game-modes",
    "HttpMethod": "GET",
    "IsController": true,
    "Order": 0,
    "Parameters": [],
    "ReturnTypes": []
  },
  {
    "ContainingType": "GAM106ASM.Controllers.GameInfoController",
    "Method": "GetAllMonsters",
    "RelativePath": "api/GameInfo/monsters",
    "HttpMethod": "GET",
    "IsController": true,
    "Order": 0,
    "Parameters": [],
    "ReturnTypes": []
  },
  {
    "ContainingType": "GAM106ASM.Controllers.GameInfoController",
    "Method": "GetOnlinePlayers",
    "RelativePath": "api/GameInfo/online-players",
    "HttpMethod": "GET",
    "IsController": true,
    "Order": 0,
    "Parameters": [],
    "ReturnTypes": []
  },
  {
    "ContainingType": "GAM106ASM.Controllers.GameInfoController",
    "Method": "GetPlayersByGameMode",
    "RelativePath": "api/GameInfo/players-by-mode/{modeId}",
    "HttpMethod": "GET",
    "IsController": true,
    "Order": 0,
    "Parameters": [
      {
        "Name": "modeId",
        "Type": "System.Int32",
        "IsRequired": true
      }
    ],
    "ReturnTypes": []
  },
  {
    "ContainingType": "GAM106ASM.Controllers.GameInfoController",
    "Method": "GetAllQuests",
    "RelativePath": "api/GameInfo/quests",
    "HttpMethod": "GET",
    "IsController": true,
    "Order": 0,
    "Parameters": [],
    "ReturnTypes": []
  },
  {
    "ContainingType": "GAM106ASM.Controllers.GameInfoController",
    "Method": "GetAllResources",
    "RelativePath": "api/GameInfo/resources",
    "HttpMethod": "GET",
    "IsController": true,
    "Order": 0,
    "Parameters": [],
    "ReturnTypes": []
  },
  {
    "ContainingType": "GAM106ASM.Controllers.GameInfoController",
    "Method": "GetResourceDetail",
    "RelativePath": "api/GameInfo/resources/{resourceId}",
    "HttpMethod": "GET",
    "IsController": true,
    "Order": 0,
    "Parameters": [
      {
        "Name": "resourceId",
        "Type": "System.Int32",
        "IsRequired": true
      }
    ],
    "ReturnTypes": []
  },
  {
    "ContainingType": "GAM106ASM.Controllers.GameInfoController",
    "Method": "GetAllVehicles",
    "RelativePath": "api/GameInfo/vehicles",
    "HttpMethod": "GET",
    "IsController": true,
    "Order": 0,
    "Parameters": [],
    "ReturnTypes": []
  },
  {
    "ContainingType": "GAM106ASM.Controllers.GameplayController",
    "Method": "AcceptQuest",
    "RelativePath": "api/Gameplay/accept-quest",
    "HttpMethod": "POST",
    "IsController": true,
    "Order": 0,
    "Parameters": [
      {
        "Name": "dto",
        "Type": "GAM106ASM.Controllers.QuestActionDto",
        "IsRequired": true
      }
    ],
    "ReturnTypes": []
  },
  {
    "ContainingType": "GAM106ASM.Controllers.GameplayController",
    "Method": "CompleteQuest",
    "RelativePath": "api/Gameplay/complete-quest",
    "HttpMethod": "POST",
    "IsController": true,
    "Order": 0,
    "Parameters": [
      {
        "Name": "dto",
        "Type": "GAM106ASM.Controllers.QuestActionDto",
        "IsRequired": true
      }
    ],
    "ReturnTypes": []
  },
  {
    "ContainingType": "GAM106ASM.Controllers.GameplayController",
    "Method": "EndGameSession",
    "RelativePath": "api/Gameplay/end-session",
    "HttpMethod": "POST",
    "IsController": true,
    "Order": 0,
    "Parameters": [
      {
        "Name": "dto",
        "Type": "GAM106ASM.Controllers.EndSessionDto",
        "IsRequired": true
      }
    ],
    "ReturnTypes": []
  },
  {
    "ContainingType": "GAM106ASM.Controllers.GameplayController",
    "Method": "GatherResource",
    "RelativePath": "api/Gameplay/gather-resource",
    "HttpMethod": "POST",
    "IsController": true,
    "Order": 0,
    "Parameters": [
      {
        "Name": "dto",
        "Type": "GAM106ASM.Controllers.GatherResourceDto",
        "IsRequired": true
      }
    ],
    "ReturnTypes": []
  },
  {
    "ContainingType": "GAM106ASM.Controllers.GameplayController",
    "Method": "KillMonster",
    "RelativePath": "api/Gameplay/kill-monster",
    "HttpMethod": "POST",
    "IsController": true,
    "Order": 0,
    "Parameters": [
      {
        "Name": "dto",
        "Type": "GAM106ASM.Controllers.KillMonsterDto",
        "IsRequired": true
      }
    ],
    "ReturnTypes": []
  },
  {
    "ContainingType": "GAM106ASM.Controllers.GameplayController",
    "Method": "StartGameSession",
    "RelativePath": "api/Gameplay/start-session",
    "HttpMethod": "POST",
    "IsController": true,
    "Order": 0,
    "Parameters": [
      {
        "Name": "dto",
        "Type": "GAM106ASM.Controllers.StartSessionDto",
        "IsRequired": true
      }
    ],
    "ReturnTypes": []
  },
  {
    "ContainingType": "GAM106ASM.Controllers.GameplayController",
    "Method": "UpdatePlayerStats",
    "RelativePath": "api/Gameplay/update-stats",
    "HttpMethod": "PUT",
    "IsController": true,
    "Order": 0,
    "Parameters": [
      {
        "Name": "dto",
        "Type": "GAM106ASM.Controllers.UpdateStatsDto",
        "IsRequired": true
      }
    ],
    "ReturnTypes": []
  },
  {
    "ContainingType": "GAM106ASM.Controllers.ItemController",
    "Method": "CreateItem",
    "RelativePath": "api/Item",
    "HttpMethod": "POST",
    "IsController": true,
    "Order": 0,
    "Parameters": [
      {
        "Name": "request",
        "Type": "GAM106ASM.Controllers.CreateItemRequest",
        "IsRequired": true
      }
    ],
    "ReturnTypes": [
      {
        "Type": "GAM106ASM.Models.ItemSalesSheet",
        "MediaTypes": [
          "text/plain",
          "application/json",
          "text/json"
        ],
        "StatusCode": 200
      }
    ]
  },
  {
    "ContainingType": "GAM106ASM.Controllers.ItemController",
    "Method": "GetItemById",
    "RelativePath": "api/Item/{id}",
    "HttpMethod": "GET",
    "IsController": true,
    "Order": 0,
    "Parameters": [
      {
        "Name": "id",
        "Type": "System.Int32",
        "IsRequired": true
      }
    ],
    "ReturnTypes": [
      {
        "Type": "GAM106ASM.Models.ItemSalesSheet",
        "MediaTypes": [
          "text/plain",
          "application/json",
          "text/json"
        ],
        "StatusCode": 200
      }
    ]
  },
  {
    "ContainingType": "GAM106ASM.Controllers.ItemController",
    "Method": "GetAffordableItems",
    "RelativePath": "api/Item/affordable/{playerId}",
    "HttpMethod": "GET",
    "IsController": true,
    "Order": 0,
    "Parameters": [
      {
        "Name": "playerId",
        "Type": "System.Int32",
        "IsRequired": true
      }
    ],
    "ReturnTypes": [
      {
        "Type": "System.Collections.Generic.IEnumerable\u00601[[System.Object, System.Private.CoreLib, Version=8.0.0.0, Culture=neutral, PublicKeyToken=7cec85d7bea7798e]]",
        "MediaTypes": [
          "text/plain",
          "application/json",
          "text/json"
        ],
        "StatusCode": 200
      }
    ]
  },
  {
    "ContainingType": "GAM106ASM.Controllers.ItemController",
    "Method": "GetDiamondItems",
    "RelativePath": "api/Item/diamond-items",
    "HttpMethod": "GET",
    "IsController": true,
    "Order": 0,
    "Parameters": [],
    "ReturnTypes": [
      {
        "Type": "System.Collections.Generic.IEnumerable\u00601[[System.Object, System.Private.CoreLib, Version=8.0.0.0, Culture=neutral, PublicKeyToken=7cec85d7bea7798e]]",
        "MediaTypes": [
          "text/plain",
          "application/json",
          "text/json"
        ],
        "StatusCode": 200
      }
    ]
  },
  {
    "ContainingType": "GAM106ASM.Controllers.ItemController",
    "Method": "GetMostPurchasedItems",
    "RelativePath": "api/Item/most-purchased",
    "HttpMethod": "GET",
    "IsController": true,
    "Order": 0,
    "Parameters": [],
    "ReturnTypes": [
      {
        "Type": "System.Collections.Generic.IEnumerable\u00601[[System.Object, System.Private.CoreLib, Version=8.0.0.0, Culture=neutral, PublicKeyToken=7cec85d7bea7798e]]",
        "MediaTypes": [
          "text/plain",
          "application/json",
          "text/json"
        ],
        "StatusCode": 200
      }
    ]
  },
  {
    "ContainingType": "GAM106ASM.Controllers.ItemController",
    "Method": "GetExpensiveWeapons",
    "RelativePath": "api/Item/weapons/expensive",
    "HttpMethod": "GET",
    "IsController": true,
    "Order": 0,
    "Parameters": [],
    "ReturnTypes": [
      {
        "Type": "System.Collections.Generic.IEnumerable\u00601[[System.Object, System.Private.CoreLib, Version=8.0.0.0, Culture=neutral, PublicKeyToken=7cec85d7bea7798e]]",
        "MediaTypes": [
          "text/plain",
          "application/json",
          "text/json"
        ],
        "StatusCode": 200
      }
    ]
  },
  {
    "ContainingType": "GAM106ASM.Controllers.PlayerController",
    "Method": "UpdatePlayerPassword",
    "RelativePath": "api/Player/{playerId}/password",
    "HttpMethod": "PUT",
    "IsController": true,
    "Order": 0,
    "Parameters": [
      {
        "Name": "playerId",
        "Type": "System.Int32",
        "IsRequired": true
      },
      {
        "Name": "request",
        "Type": "GAM106ASM.Controllers.UpdatePasswordRequest",
        "IsRequired": true
      }
    ],
    "ReturnTypes": []
  },
  {
    "ContainingType": "GAM106ASM.Controllers.PlayerController",
    "Method": "GetPlayersByGameMode",
    "RelativePath": "api/Player/by-game-mode/{modeName}",
    "HttpMethod": "GET",
    "IsController": true,
    "Order": 0,
    "Parameters": [
      {
        "Name": "modeName",
        "Type": "System.String",
        "IsRequired": true
      }
    ],
    "ReturnTypes": [
      {
        "Type": "System.Collections.Generic.IEnumerable\u00601[[System.Object, System.Private.CoreLib, Version=8.0.0.0, Culture=neutral, PublicKeyToken=7cec85d7bea7798e]]",
        "MediaTypes": [
          "text/plain",
          "application/json",
          "text/json"
        ],
        "StatusCode": 200
      }
    ]
  },
  {
    "ContainingType": "GAM106ASM.Controllers.PlayerController",
    "Method": "GetPlayersWithPurchaseCount",
    "RelativePath": "api/Player/purchase-count",
    "HttpMethod": "GET",
    "IsController": true,
    "Order": 0,
    "Parameters": [],
    "ReturnTypes": [
      {
        "Type": "System.Collections.Generic.IEnumerable\u00601[[System.Object, System.Private.CoreLib, Version=8.0.0.0, Culture=neutral, PublicKeyToken=7cec85d7bea7798e]]",
        "MediaTypes": [
          "text/plain",
          "application/json",
          "text/json"
        ],
        "StatusCode": 200
      }
    ]
  },
  {
    "ContainingType": "GAM106ASM.Controllers.PlayerController",
    "Method": "RequestPasswordReset",
    "RelativePath": "api/Player/request-password-reset",
    "HttpMethod": "POST",
    "IsController": true,
    "Order": 0,
    "Parameters": [
      {
        "Name": "request",
        "Type": "GAM106ASM.Controllers.RequestPasswordResetRequest",
        "IsRequired": true
      }
    ],
    "ReturnTypes": []
  },
  {
    "ContainingType": "GAM106ASM.Controllers.PlayerController",
    "Method": "ResetPassword",
    "RelativePath": "api/Player/reset-password",
    "HttpMethod": "POST",
    "IsController": true,
    "Order": 0,
    "Parameters": [
      {
        "Name": "request",
        "Type": "GAM106ASM.Controllers.ResetPasswordRequest",
        "IsRequired": true
      }
    ],
    "ReturnTypes": []
  },
  {
    "ContainingType": "GAM106ASM.Controllers.ResourceController",
    "Method": "GetAllResources",
    "RelativePath": "api/Resource",
    "HttpMethod": "GET",
    "IsController": true,
    "Order": 0,
    "Parameters": [],
    "ReturnTypes": [
      {
        "Type": "System.Collections.Generic.IEnumerable\u00601[[GAM106ASM.Models.Resource, GAM106ASM, Version=1.0.0.0, Culture=neutral, PublicKeyToken=null]]",
        "MediaTypes": [
          "text/plain",
          "application/json",
          "text/json"
        ],
        "StatusCode": 200
      }
    ]
  },
  {
    "ContainingType": "GAM106ASM.Controllers.ShopController",
    "Method": "GetAffordableItems",
    "RelativePath": "api/Shop/affordable/{playerId}",
    "HttpMethod": "GET",
    "IsController": true,
    "Order": 0,
    "Parameters": [
      {
        "Name": "playerId",
        "Type": "System.Int32",
        "IsRequired": true
      }
    ],
    "ReturnTypes": []
  },
  {
    "ContainingType": "GAM106ASM.Controllers.ShopController",
    "Method": "GetHotItems",
    "RelativePath": "api/Shop/hot",
    "HttpMethod": "GET",
    "IsController": true,
    "Order": 0,
    "Parameters": [],
    "ReturnTypes": []
  },
  {
    "ContainingType": "GAM106ASM.Controllers.ShopController",
    "Method": "GetPremiumItems",
    "RelativePath": "api/Shop/premium",
    "HttpMethod": "GET",
    "IsController": true,
    "Order": 0,
    "Parameters": [],
    "ReturnTypes": []
  },
  {
    "ContainingType": "GAM106ASM.Controllers.ShopController",
    "Method": "PurchaseItem",
    "RelativePath": "api/Shop/purchase",
    "HttpMethod": "POST",
    "IsController": true,
    "Order": 0,
    "Parameters": [
      {
        "Name": "dto",
        "Type": "GAM106ASM.Controllers.PurchaseDto",
        "IsRequired": true
      }
    ],
    "ReturnTypes": []
  },
  {
    "ContainingType": "GAM106ASM.Controllers.ShopController",
    "Method": "PurchaseVehicle",
    "RelativePath": "api/Shop/purchase-vehicle",
    "HttpMethod": "POST",
    "IsController": true,
    "Order": 0,
    "Parameters": [
      {
        "Name": "dto",
        "Type": "GAM106ASM.Controllers.PurchaseVehicleDto",
        "IsRequired": true
      }
    ],
    "ReturnTypes": []
  },
  {
    "ContainingType": "GAM106ASM.Controllers.ShopController",
    "Method": "SearchItems",
    "RelativePath": "api/Shop/search",
    "HttpMethod": "GET",
    "IsController": true,
    "Order": 0,
    "Parameters": [
      {
        "Name": "name",
        "Type": "System.String",
        "IsRequired": false
      },
      {
        "Name": "maxPrice",
        "Type": "System.Nullable\u00601[[System.Int32, System.Private.CoreLib, Version=8.0.0.0, Culture=neutral, PublicKeyToken=7cec85d7bea7798e]]",
        "IsRequired": false
      }
    ],
    "ReturnTypes": []
  },
  {
    "ContainingType": "GAM106ASM.Controllers.TransactionController",
    "Method": "GetAllTransactions",
    "RelativePath": "api/Transaction",
    "HttpMethod": "GET",
    "IsController": true,
    "Order": 0,
    "Parameters": [],
    "ReturnTypes": [
      {
        "Type": "System.Collections.Generic.IEnumerable\u00601[[GAM106ASM.Models.Transaction, GAM106ASM, Version=1.0.0.0, Culture=neutral, PublicKeyToken=null]]",
        "MediaTypes": [
          "text/plain",
          "application/json",
          "text/json"
        ],
        "StatusCode": 200
      }
    ]
  },
  {
    "ContainingType": "GAM106ASM.Controllers.TransactionController",
    "Method": "GetPlayerTransactions",
    "RelativePath": "api/Transaction/player/{playerId}",
    "HttpMethod": "GET",
    "IsController": true,
    "Order": 0,
    "Parameters": [
      {
        "Name": "playerId",
        "Type": "System.Int32",
        "IsRequired": true
      }
    ],
    "ReturnTypes": [
      {
        "Type": "System.Collections.Generic.IEnumerable\u00601[[System.Object, System.Private.CoreLib, Version=8.0.0.0, Culture=neutral, PublicKeyToken=7cec85d7bea7798e]]",
        "MediaTypes": [
          "text/plain",
          "application/json",
          "text/json"
        ],
        "StatusCode": 200
      }
    ]
  }
]